cli/__init__.py
cli/auth.py
cli/config.py
cli/main.py
cli/build/lib/commands/__init__.py
cli/build/lib/commands/generate.py
cli/build/lib/commands/offline.py
cli/build/lib/commands/online.py
cli/build/lib/commands/useless.py
cli/build/lib/commands/utils.py
cli/commands/__init__.py
cli/commands/generate.py
cli/commands/offline.py
cli/commands/online.py
cli/commands/useless.py
cli/commands/utils.py
test_enie-0.2.1.dist-info/METADATA
test_enie-0.2.1.dist-info/WHEEL
test_enie-0.2.1.dist-info/entry_points.txt
test_enie-0.2.1.dist-info/top_level.txt
test_enie-0.2.1.dist-info/RECORD
