Metadata-Version: 2.4
Name: test_-enie
Version: 0.2.1
Summary: CLI tool to auto-generate test cases for your code
Author-email: Kushagra Wadhwa <testgenieofficial@gmail.com>
License-Expression: MIT
Requires-Python: >=3.7
Requires-Dist: click==8.1.7
Requires-Dist: requests==2.31.0
Requires-Dist: pathlib2==2.3.7
